cirve/__init__.py
cirve/circuito.py
cirve/elementos.py
cirve/errors.py
cirve/graph.py
cirve/subcircuito.py
cirve-0.2.dist-info/METADATA
cirve-0.2.dist-info/RECORD
cirve-0.2.dist-info/WHEEL
cirve-0.2.dist-info/top_level.txt
